{
  "goturkeytourism": {
    "count": 0,
    "last_updated": ""
  },
  "malaysia.travel.sg": {
    "count": 0,
    "last_updated": ""
  },
  "TheSmartLocal": {
    "count": 0,
    "last_updated": ""
  },
  "Tripviss": {
    "count": 0,
    "last_updated": ""
  },
  "koreatourism": {
    "count": 0,
    "last_updated": ""
  },
  "indonesia.travel": {
    "count": 0,
    "last_updated": ""
  },
  "incredibleindia": {
    "count": 0,
    "last_updated": ""
  },
  "visitjapaninternational": {
    "count": 0,
    "last_updated": ""
  },
  "wonderfulplacesindo": {
    "count": 0,
    "last_updated": ""
  },
  "itsmorefuninthePhilippines": {
    "count": 0,
    "last_updated": ""
  },
  "DiscoverHongKong": {
    "count": 0,
    "last_updated": ""
  },
  "visitchinanow": {
    "count": 0,
    "last_updated": ""
  }
}